portal/__init__.py
portal/model.py
portal/networks.py
portal/utils.py
portal_sc-1.0.4.dist-info/LICENSE
portal_sc-1.0.4.dist-info/METADATA
portal_sc-1.0.4.dist-info/WHEEL
portal_sc-1.0.4.dist-info/top_level.txt
portal_sc-1.0.4.dist-info/RECORD
