Metadata-Version: 2.1
Name: portal-sc
Version: 1.0.4
Summary: An efficient, accurate and flexible method for single-cell data integration.
Home-page: https://github.com/YangLabHKUST/Portal
Author: Jia Zhao
Author-email: jzhaoaz@connect.ust.hk
License: MIT
Requires-Python: >=3.7
License-File: LICENSE
Requires-Dist: torch ==1.8.1
Requires-Dist: scanpy ==1.7.2
Requires-Dist: anndata ==0.7.6
Requires-Dist: scipy >=1.6.2
Requires-Dist: scikit-learn >=0.24.1
Requires-Dist: numpy >=1.19.2
Requires-Dist: pandas >=1.1.5
Requires-Dist: statsmodels >=0.12.2
Requires-Dist: louvain ==0.7.0
Requires-Dist: umap-learn ==0.4.6
Requires-Dist: numba ==0.49.1
Requires-Dist: tables ==3.6.1
Requires-Dist: scikit-misc ==0.1.3
